Workbook

Sheet Sales Data
A1: Order Date | B1: Order ID | C1: Product | D1: Category | E1: Region | F1: Quantity | G1: Unit Price (₹) | H1: Discount % | I1: Revenue (₹) | J1: Cost (₹) | K1: Profit (₹) | L1: Customer Segment
A2: 45985 | B2: TH-0001 | C2: Wireless Mouse | D2: Accessories | E2: South | F2: 1 | G2: 850 | H2: 0.05 | I2: 807.5 | J2: 387.6 | K2: 419.9 | L2: Consumer
A3: 45729 | B3: TH-0002 | C3: Desk Lamp | D3: Furniture | E3: North | F3: 1 | G3: 1450 | H3: 0.12 | I3: 1276 | J3: 535.92 | K3: 740.08 | L3: Small Business
A4: 45874 | B4: TH-0003 | C4: Laptop | D4: Electronics | E4: South | F4: 1 | G4: 42000 | H4: 0.02 | I4: 41160 | J4: 29635.2 | K4: 11524.8 | L4: Small Business
A5: 45966 | B5: TH-0004 | C5: Laptop | D5: Electronics | E5: West | F5: 3 | G5: 42000 | H5: 0.12 | I5: 110880 | J5: 79833.6 | K5: 31046.4 | L5: Consumer
A6: 45887 | B6: TH-0005 | C6: Notebook Pack | D6: Stationery | E6: North | F6: 2 | G6: 320 | H6: 0.15 | I6: 544 | J6: 190.4 | K6: 353.6 | L6: Consumer
A7: 46015 | B7: TH-0006 | C7: Headphones | D7: Electronics | E7: South | F7: 2 | G7: 3200 | H7: 0.02 | I7: 6272 | J7: 3888.64 | K7: 2383.36 | L7: Corporate
A8: 45710 | B8: TH-0007 | C8: Wireless Mouse | D8: Accessories | E8: East | F8: 2 | G8: 850 | H8: 0.05 | I8: 1615 | J8: 775.2 | K8: 839.8 | L8: Small Business
A9: 45793 | B9: TH-0008 | C9: Laptop | D9: Electronics | E9: North | F9: 4 | G9: 42000 | H9: 0.1 | I9: 151200 | J9: 108864 | K9: 42336 | L9: Corporate
A10: 45698 | B10: TH-0009 | C10: Webcam | D10: Electronics | E10: East | F10: 2 | G10: 4100 | H10: 0.12 | I10: 7216 | J10: 4329.6 | K10: 2886.4 | L10: Small Business
A11: 45756 | B11: TH-0010 | C11: Desk Lamp | D11: Furniture | E11: South | F11: 1 | G11: 1450 | H11: 0.12 | I11: 1276 | J11: 535.92 | K11: 740.08 | L11: Corporate
A12: 45698 | B12: TH-0011 | C12: Monitor | D12: Electronics | E12: East | F12: 6 | G12: 12500 | H12: 0.08 | I12: 69000 | J12: 46230 | K12: 22770 | L12: Corporate
A13: 45983 | B13: TH-0012 | C13: Desk | D13: Furniture | E13: South | F13: 1 | G13: 9500 | H13: 0.05 | I13: 9025 | J13: 4963.75 | K13: 4061.25 | L13: Small Business
... A301: 45932 | B301: TH-0300 | C301: Laptop | D301: Electronics | E301: South | F301: 4 | G301: 42000 | H301: 0.1 | I301: 151200 | J301: 108864 | K301: 42336 | L301: Small Business

Sheet Dashboard
A1: THIRANEX | SALES & REVENUE ANALYSIS DASHBOARD | J1: Product | K1: Revenue (₹)
A2: Sample training dataset • Jan–Dec 2025 • Change filters to explore | J2: Laptop | K2: =SUMPRODUCT(('Sales Data'!$C$2:$C$301=J2)*(IF($B$4="All",1,'Sales Data'!$E$2:$E$301=$B$4))*(IF($E$4="All",1,'Sales Data'!$D$2:$D$301=$E$4))*'Sales Data'!$I$2:$I$301)
J3: Wireless Mouse | K3: =SUMPRODUCT(('Sales Data'!$C$2:$C$301=J3)*(IF($B$4="All",1,'Sales Data'!$E$2:$E$301=$B$4))*(IF($E$4="All",1,'Sales Data'!$D$2:$D$301=$E$4))*'Sales Data'!$I$2:$I$301)
A4: Region Filter | B4: All | D4: Category Filter | E4: All | J4: Keyboard | K4: =SUMPRODUCT(('Sales Data'!$C$2:$C$301=J4)*(IF($B$4="All",1,'Sales Data'!$E$2:$E$301=$B$4))*(IF($E$4="All",1,'Sales Data'!$D$2:$D$301=$E$4))*'Sales Data'!$I$2:$I$301)
J5: Monitor | K5: =SUMPRODUCT(('Sales Data'!$C$2:$C$301=J5)*(IF($B$4="All",1,'Sales Data'!$E$2:$E$301=$B$4))*(IF($E$4="All",1,'Sales Data'!$D$2:$D$301=$E$4))*'Sales Data'!$I$2:$I$301)
A6: TOTAL REVENUE | C6: TOTAL PROFIT | E6: TOTAL ORDERS | G6: UNITS SOLD | J6: Office Chair | K6: =SUMPRODUCT(('Sales Data'!$C$2:$C$301=J6)*(IF($B$4="All",1,'Sales Data'!$E$2:$E$301=$B$4))*(IF($E$4="All",1,'Sales Data'!$D$2:$D$301=$E$4))*'Sales Data'!$I$2:$I$301)
A7: =SUMPRODUCT((IF($B$4="All",1,'Sales Data'!$E$2:$E$301=$B$4))*(IF($E$4="All",1,'Sales Data'!$D$2:$D$301=$E$4))*'Sales Data'!$I$2:$I$301) | C7: =SUMPRODUCT((IF($B$4="All",1,'Sales Data'!$E$2:$E$301=$B$4))*(IF($E$4="All",1,'Sales Data'!$D$2:$D$301=$E$4))*'Sales Data'!$K$2:$K$301) | E7: =SUMPRODUCT((IF($B$4="All",1,'Sales Data'!$E$2:$E$301=$B$4))*(IF($E$4="All",1,'Sales Data'!$D$2:$D$301=$E$4))) | G7: =SUMPRODUCT((IF($B$4="All",1,'Sales Data'!$E$2:$E$301=$B$4))*(IF($E$4="All",1,'Sales Data'!$D$2:$D$301=$E$4))*'Sales Data'!$F$2:$F$301) | J7: Desk | K7: =SUMPRODUCT(('Sales Data'!$C$2:$C$301=J7)*(IF($B$4="All",1,'Sales Data'!$E$2:$E$301=$B$4))*(IF($E$4="All",1,'Sales Data'!$D$2:$D$301=$E$4))*'Sales Data'!$I$2:$I$301)
J8: Headphones | K8: =SUMPRODUCT(('Sales Data'!$C$2:$C$301=J8)*(IF($B$4="All",1,'Sales Data'!$E$2:$E$301=$B$4))*(IF($E$4="All",1,'Sales Data'!$D$2:$D$301=$E$4))*'Sales Data'!$I$2:$I$301)
J9: USB-C Hub | K9: =SUMPRODUCT(('Sales Data'!$C$2:$C$301=J9)*(IF($B$4="All",1,'Sales Data'!$E$2:$E$301=$B$4))*(IF($E$4="All",1,'Sales Data'!$D$2:$D$301=$E$4))*'Sales Data'!$I$2:$I$301)
J10: Webcam | K10: =SUMPRODUCT(('Sales Data'!$C$2:$C$301=J10)*(IF($B$4="All",1,'Sales Data'!$E$2:$E$301=$B$4))*(IF($E$4="All",1,'Sales Data'!$D$2:$D$301=$E$4))*'Sales Data'!$I$2:$I$301)
J11: Notebook Pack | K11: =SUMPRODUCT(('Sales Data'!$C$2:$C$301=J11)*(IF($B$4="All",1,'Sales Data'!$E$2:$E$301=$B$4))*(IF($E$4="All",1,'Sales Data'!$D$2:$D$301=$E$4))*'Sales Data'!$I$2:$I$301)
J12: Printer | K12: =SUMPRODUCT(('Sales Data'!$C$2:$C$301=J12)*(IF($B$4="All",1,'Sales Data'!$E$2:$E$301=$B$4))*(IF($E$4="All",1,'Sales Data'!$D$2:$D$301=$E$4))*'Sales Data'!$I$2:$I$301)
J13: Desk Lamp | K13: =SUMPRODUCT(('Sales Data'!$C$2:$C$301=J13)*(IF($B$4="All",1,'Sales Data'!$E$2:$E$301=$B$4))*(IF($E$4="All",1,'Sales Data'!$D$2:$D$301=$E$4))*'Sales Data'!$I$2:$I$301)
J16: Category | K16: Revenue (₹)
J17: Electronics | K17: =SUMPRODUCT(('Sales Data'!$D$2:$D$301=J17)*(IF($B$4="All",1,'Sales Data'!$E$2:$E$301=$B$4))*(IF($E$4="All",1,'Sales Data'!$D$2:$D$301=$E$4))*'Sales Data'!$I$2:$I$301)
J18: Accessories | K18: =SUMPRODUCT(('Sales Data'!$D$2:$D$301=J18)*(IF($B$4="All",1,'Sales Data'!$E$2:$E$301=$B$4))*(IF($E$4="All",1,'Sales Data'!$D$2:$D$301=$E$4))*'Sales Data'!$I$2:$I$301)
J19: Furniture | K19: =SUMPRODUCT(('Sales Data'!$D$2:$D$301=J19)*(IF($B$4="All",1,'Sales Data'!$E$2:$E$301=$B$4))*(IF($E$4="All",1,'Sales Data'!$D$2:$D$301=$E$4))*'Sales Data'!$I$2:$I$301)
J20: Stationery | K20: =SUMPRODUCT(('Sales Data'!$D$2:$D$301=J20)*(IF($B$4="All",1,'Sales Data'!$E$2:$E$301=$B$4))*(IF($E$4="All",1,'Sales Data'!$D$2:$D$301=$E$4))*'Sales Data'!$I$2:$I$301)

Sheet Monthly Summary
A1: Month | B1: Revenue (₹) | C1: Profit (₹) | D1: Orders
A2: 45658 | B2: =SUMPRODUCT(('Sales Data'!$A$2:$A$301>=A2)*('Sales Data'!$A$2:$A$301<EDATE(A2,1))*(IF(Dashboard!$B$4="All",1,'Sales Data'!$E$2:$E$301=Dashboard!$B$4))*(IF(Dashboard!$E$4="All",1,'Sales Data'!$D$2:$D$301=Dashboard!$E$4))*'Sales Data'!$I$2:$I$301) | C2: =SUMPRODUCT(('Sales Data'!$A$2:$A$301>=A2)*('Sales Data'!$A$2:$A$301<EDATE(A2,1))*(IF(Dashboard!$B$4="All",1,'Sales Data'!$E$2:$E$301=Dashboard!$B$4))*(IF(Dashboard!$E$4="All",1,'Sales Data'!$D$2:$D$301=Dashboard!$E$4))*'Sales Data'!$K$2:$K$301) | D2: =SUMPRODUCT(('Sales Data'!$A$2:$A$301>=A2)*('Sales Data'!$A$2:$A$301<EDATE(A2,1))*(IF(Dashboard!$B$4="All",1,'Sales Data'!$E$2:$E$301=Dashboard!$B$4))*(IF(Dashboard!$E$4="All",1,'Sales Data'!$D$2:$D$301=Dashboard!$E$4)))
A3: 45689 | B3: =SUMPRODUCT(('Sales Data'!$A$2:$A$301>=A3)*('Sales Data'!$A$2:$A$301<EDATE(A3,1))*(IF(Dashboard!$B$4="All",1,'Sales Data'!$E$2:$E$301=Dashboard!$B$4))*(IF(Dashboard!$E$4="All",1,'Sales Data'!$D$2:$D$301=Dashboard!$E$4))*'Sales Data'!$I$2:$I$301) | C3: =SUMPRODUCT(('Sales Data'!$A$2:$A$301>=A3)*('Sales Data'!$A$2:$A$301<EDATE(A3,1))*(IF(Dashboard!$B$4="All",1,'Sales Data'!$E$2:$E$301=Dashboard!$B$4))*(IF(Dashboard!$E$4="All",1,'Sales Data'!$D$2:$D$301=Dashboard!$E$4))*'Sales Data'!$K$2:$K$301) | D3: =SUMPRODUCT(('Sales Data'!$A$2:$A$301>=A3)*('Sales Data'!$A$2:$A$301<EDATE(A3,1))*(IF(Dashboard!$B$4="All",1,'Sales Data'!$E$2:$E$301=Dashboard!$B$4))*(IF(Dashboard!$E$4="All",1,'Sales Data'!$D$2:$D$301=Dashboard!$E$4)))
A4: 45717 | B4: =SUMPRODUCT(('Sales Data'!$A$2:$A$301>=A4)*('Sales Data'!$A$2:$A$301<EDATE(A4,1))*(IF(Dashboard!$B$4="All",1,'Sales Data'!$E$2:$E$301=Dashboard!$B$4))*(IF(Dashboard!$E$4="All",1,'Sales Data'!$D$2:$D$301=Dashboard!$E$4))*'Sales Data'!$I$2:$I$301) | C4: =SUMPRODUCT(('Sales Data'!$A$2:$A$301>=A4)*('Sales Data'!$A$2:$A$301<EDATE(A4,1))*(IF(Dashboard!$B$4="All",1,'Sales Data'!$E$2:$E$301=Dashboard!$B$4))*(IF(Dashboard!$E$4="All",1,'Sales Data'!$D$2:$D$301=Dashboard!$E$4))*'Sales Data'!$K$2:$K$301) | D4: =SUMPRODUCT(('Sales Data'!$A$2:$A$301>=A4)*('Sales Data'!$A$2:$A$301<EDATE(A4,1))*(IF(Dashboard!$B$4="All",1,'Sales Data'!$E$2:$E$301=Dashboard!$B$4))*(IF(Dashboard!$E$4="All",1,'Sales Data'!$D$2:$D$301=Dashboard!$E$4)))
A5: 45748 | B5: =SUMPRODUCT(('Sales Data'!$A$2:$A$301>=A5)*('Sales Data'!$A$2:$A$301<EDATE(A5,1))*(IF(Dashboard!$B$4="All",1,'Sales Data'!$E$2:$E$301=Dashboard!$B$4))*(IF(Dashboard!$E$4="All",1,'Sales Data'!$D$2:$D$301=Dashboard!$E$4))*'Sales Data'!$I$2:$I$301) | C5: =SUMPRODUCT(('Sales Data'!$A$2:$A$301>=A5)*('Sales Data'!$A$2:$A$301<EDATE(A5,1))*(IF(Dashboard!$B$4="All",1,'Sales Data'!$E$2:$E$301=Dashboard!$B$4))*(IF(Dashboard!$E$4="All",1,'Sales Data'!$D$2:$D$301=Dashboard!$E$4))*'Sales Data'!$K$2:$K$301) | D5: =SUMPRODUCT(('Sales Data'!$A$2:$A$301>=A5)*('Sales Data'!$A$2:$A$301<EDATE(A5,1))*(IF(Dashboard!$B$4="All",1,'Sales Data'!$E$2:$E$301=Dashboard!$B$4))*(IF(Dashboard!$E$4="All",1,'Sales Data'!$D$2:$D$301=Dashboard!$E$4)))
A6: 45778 | B6: =SUMPRODUCT(('Sales Data'!$A$2:$A$301>=A6)*('Sales Data'!$A$2:$A$301<EDATE(A6,1))*(IF(Dashboard!$B$4="All",1,'Sales Data'!$E$2:$E$301=Dashboard!$B$4))*(IF(Dashboard!$E$4="All",1,'Sales Data'!$D$2:$D$301=Dashboard!$E$4))*'Sales Data'!$I$2:$I$301) | C6: =SUMPRODUCT(('Sales Data'!$A$2:$A$301>=A6)*('Sales Data'!$A$2:$A$301<EDATE(A6,1))*(IF(Dashboard!$B$4="All",1,'Sales Data'!$E$2:$E$301=Dashboard!$B$4))*(IF(Dashboard!$E$4="All",1,'Sales Data'!$D$2:$D$301=Dashboard!$E$4))*'Sales Data'!$K$2:$K$301) | D6: =SUMPRODUCT(('Sales Data'!$A$2:$A$301>=A6)*('Sales Data'!$A$2:$A$301<EDATE(A6,1))*(IF(Dashboard!$B$4="All",1,'Sales Data'!$E$2:$E$301=Dashboard!$B$4))*(IF(Dashboard!$E$4="All",1,'Sales Data'!$D$2:$D$301=Dashboard!$E$4)))
A7: 45809 | B7: =SUMPRODUCT(('Sales Data'!$A$2:$A$301>=A7)*('Sales Data'!$A$2:$A$301<EDATE(A7,1))*(IF(Dashboard!$B$4="All",1,'Sales Data'!$E$2:$E$301=Dashboard!$B$4))*(IF(Dashboard!$E$4="All",1,'Sales Data'!$D$2:$D$301=Dashboard!$E$4))*'Sales Data'!$I$2:$I$301) | C7: =SUMPRODUCT(('Sales Data'!$A$2:$A$301>=A7)*('Sales Data'!$A$2:$A$301<EDATE(A7,1))*(IF(Dashboard!$B$4="All",1,'Sales Data'!$E$2:$E$301=Dashboard!$B$4))*(IF(Dashboard!$E$4="All",1,'Sales Data'!$D$2:$D$301=Dashboard!$E$4))*'Sales Data'!$K$2:$K$301) | D7: =SUMPRODUCT(('Sales Data'!$A$2:$A$301>=A7)*('Sales Data'!$A$2:$A$301<EDATE(A7,1))*(IF(Dashboard!$B$4="All",1,'Sales Data'!$E$2:$E$301=Dashboard!$B$4))*(IF(Dashboard!$E$4="All",1,'Sales Data'!$D$2:$D$301=Dashboard!$E$4)))
A8: 45839 | B8: =SUMPRODUCT(('Sales Data'!$A$2:$A$301>=A8)*('Sales Data'!$A$2:$A$301<EDATE(A8,1))*(IF(Dashboard!$B$4="All",1,'Sales Data'!$E$2:$E$301=Dashboard!$B$4))*(IF(Dashboard!$E$4="All",1,'Sales Data'!$D$2:$D$301=Dashboard!$E$4))*'Sales Data'!$I$2:$I$301) | C8: =SUMPRODUCT(('Sales Data'!$A$2:$A$301>=A8)*('Sales Data'!$A$2:$A$301<EDATE(A8,1))*(IF(Dashboard!$B$4="All",1,'Sales Data'!$E$2:$E$301=Dashboard!$B$4))*(IF(Dashboard!$E$4="All",1,'Sales Data'!$D$2:$D$301=Dashboard!$E$4))*'Sales Data'!$K$2:$K$301) | D8: =SUMPRODUCT(('Sales Data'!$A$2:$A$301>=A8)*('Sales Data'!$A$2:$A$301<EDATE(A8,1))*(IF(Dashboard!$B$4="All",1,'Sales Data'!$E$2:$E$301=Dashboard!$B$4))*(IF(Dashboard!$E$4="All",1,'Sales Data'!$D$2:$D$301=Dashboard!$E$4)))
A9: 45870 | B9: =SUMPRODUCT(('Sales Data'!$A$2:$A$301>=A9)*('Sales Data'!$A$2:$A$301<EDATE(A9,1))*(IF(Dashboard!$B$4="All",1,'Sales Data'!$E$2:$E$301=Dashboard!$B$4))*(IF(Dashboard!$E$4="All",1,'Sales Data'!$D$2:$D$301=Dashboard!$E$4))*'Sales Data'!$I$2:$I$301) | C9: =SUMPRODUCT(('Sales Data'!$A$2:$A$301>=A9)*('Sales Data'!$A$2:$A$301<EDATE(A9,1))*(IF(Dashboard!$B$4="All",1,'Sales Data'!$E$2:$E$301=Dashboard!$B$4))*(IF(Dashboard!$E$4="All",1,'Sales Data'!$D$2:$D$301=Dashboard!$E$4))*'Sales Data'!$K$2:$K$301) | D9: =SUMPRODUCT(('Sales Data'!$A$2:$A$301>=A9)*('Sales Data'!$A$2:$A$301<EDATE(A9,1))*(IF(Dashboard!$B$4="All",1,'Sales Data'!$E$2:$E$301=Dashboard!$B$4))*(IF(Dashboard!$E$4="All",1,'Sales Data'!$D$2:$D$301=Dashboard!$E$4)))
A10: 45901 | B10: =SUMPRODUCT(('Sales Data'!$A$2:$A$301>=A10)*('Sales Data'!$A$2:$A$301<EDATE(A10,1))*(IF(Dashboard!$B$4="All",1,'Sales Data'!$E$2:$E$301=Dashboard!$B$4))*(IF(Dashboard!$E$4="All",1,'Sales Data'!$D$2:$D$301=Dashboard!$E$4))*'Sales Data'!$I$2:$I$301) | C10: =SUMPRODUCT(('Sales Data'!$A$2:$A$301>=A10)*('Sales Data'!$A$2:$A$301<EDATE(A10,1))*(IF(Dashboard!$B$4="All",1,'Sales Data'!$E$2:$E$301=Dashboard!$B$4))*(IF(Dashboard!$E$4="All",1,'Sales Data'!$D$2:$D$301=Dashboard!$E$4))*'Sales Data'!$K$2:$K$301) | D10: =SUMPRODUCT(('Sales Data'!$A$2:$A$301>=A10)*('Sales Data'!$A$2:$A$301<EDATE(A10,1))*(IF(Dashboard!$B$4="All",1,'Sales Data'!$E$2:$E$301=Dashboard!$B$4))*(IF(Dashboard!$E$4="All",1,'Sales Data'!$D$2:$D$301=Dashboard!$E$4)))
A11: 45931 | B11: =SUMPRODUCT(('Sales Data'!$A$2:$A$301>=A11)*('Sales Data'!$A$2:$A$301<EDATE(A11,1))*(IF(Dashboard!$B$4="All",1,'Sales Data'!$E$2:$E$301=Dashboard!$B$4))*(IF(Dashboard!$E$4="All",1,'Sales Data'!$D$2:$D$301=Dashboard!$E$4))*'Sales Data'!$I$2:$I$301) | C11: =SUMPRODUCT(('Sales Data'!$A$2:$A$301>=A11)*('Sales Data'!$A$2:$A$301<EDATE(A11,1))*(IF(Dashboard!$B$4="All",1,'Sales Data'!$E$2:$E$301=Dashboard!$B$4))*(IF(Dashboard!$E$4="All",1,'Sales Data'!$D$2:$D$301=Dashboard!$E$4))*'Sales Data'!$K$2:$K$301) | D11: =SUMPRODUCT(('Sales Data'!$A$2:$A$301>=A11)*('Sales Data'!$A$2:$A$301<EDATE(A11,1))*(IF(Dashboard!$B$4="All",1,'Sales Data'!$E$2:$E$301=Dashboard!$B$4))*(IF(Dashboard!$E$4="All",1,'Sales Data'!$D$2:$D$301=Dashboard!$E$4)))
A12: 45962 | B12: =SUMPRODUCT(('Sales Data'!$A$2:$A$301>=A12)*('Sales Data'!$A$2:$A$301<EDATE(A12,1))*(IF(Dashboard!$B$4="All",1,'Sales Data'!$E$2:$E$301=Dashboard!$B$4))*(IF(Dashboard!$E$4="All",1,'Sales Data'!$D$2:$D$301=Dashboard!$E$4))*'Sales Data'!$I$2:$I$301) | C12: =SUMPRODUCT(('Sales Data'!$A$2:$A$301>=A12)*('Sales Data'!$A$2:$A$301<EDATE(A12,1))*(IF(Dashboard!$B$4="All",1,'Sales Data'!$E$2:$E$301=Dashboard!$B$4))*(IF(Dashboard!$E$4="All",1,'Sales Data'!$D$2:$D$301=Dashboard!$E$4))*'Sales Data'!$K$2:$K$301) | D12: =SUMPRODUCT(('Sales Data'!$A$2:$A$301>=A12)*('Sales Data'!$A$2:$A$301<EDATE(A12,1))*(IF(Dashboard!$B$4="All",1,'Sales Data'!$E$2:$E$301=Dashboard!$B$4))*(IF(Dashboard!$E$4="All",1,'Sales Data'!$D$2:$D$301=Dashboard!$E$4)))
A13: 45992 | B13: =SUMPRODUCT(('Sales Data'!$A$2:$A$301>=A13)*('Sales Data'!$A$2:$A$301<EDATE(A13,1))*(IF(Dashboard!$B$4="All",1,'Sales Data'!$E$2:$E$301=Dashboard!$B$4))*(IF(Dashboard!$E$4="All",1,'Sales Data'!$D$2:$D$301=Dashboard!$E$4))*'Sales Data'!$I$2:$I$301) | C13: =SUMPRODUCT(('Sales Data'!$A$2:$A$301>=A13)*('Sales Data'!$A$2:$A$301<EDATE(A13,1))*(IF(Dashboard!$B$4="All",1,'Sales Data'!$E$2:$E$301=Dashboard!$B$4))*(IF(Dashboard!$E$4="All",1,'Sales Data'!$D$2:$D$301=Dashboard!$E$4))*'Sales Data'!$K$2:$K$301) | D13: =SUMPRODUCT(('Sales Data'!$A$2:$A$301>=A13)*('Sales Data'!$A$2:$A$301<EDATE(A13,1))*(IF(Dashboard!$B$4="All",1,'Sales Data'!$E$2:$E$301=Dashboard!$B$4))*(IF(Dashboard!$E$4="All",1,'Sales Data'!$D$2:$D$301=Dashboard!$E$4)))

Sheet Read Me
A1: THIRANEX TASK 1 — COMPLETION GUIDE
A3: 1. Open the workbook | B3: Open this file in Microsoft Excel (desktop Excel recommended). Enable editing if prompted.
A4: 2. Explore the data | B4: Go to Sales Data. The workbook contains 300 sample orders across 2025, with products, categories, regions, quantities, revenue, costs and profit.
A5: 3. Use dashboard filters | B5: Go to Dashboard. Change the blue dropdown cells B4 (Region) and E4 (Category) to filter KPIs and charts. Choose All to reset.
A6: 4. Refresh / recalculate | B6: Formulas recalculate when the workbook opens in Excel. If needed, press Ctrl+Alt+F9.
A7: 5. Review the insights | B7: Compare monthly revenue, product revenue, and category contribution. Write 3–4 observations in your submission notes.
A8: 6. Capture screenshots | B8: Take a clear screenshot of the Dashboard and, if required, the Sales Data table. Make sure filters and KPI values are visible.
A9: 7. Submit on Thiranex | B9: On the task card, click Submit Work. Upload this workbook if accepted, plus any requested PDF/screenshots. Add a short project description.
A12: Important | B12: This workbook uses a generated sample dataset for practice. Do not claim it is company-provided or real business data. If Thiranex later supplies a dataset, replace the sample data and validate the results.
